chunking_contrib/pdftext/extraction.py
chunking_contrib/pdftext/pdf/chars.py
chunking_contrib/pdftext/pdf/links.py
chunking_contrib/pdftext/pdf/pages.py
chunking_contrib/pdftext/pdf/utils.py
chunking_contrib/pdftext/postprocessing.py
chunking_contrib/pdftext/schema.py
chunking_contrib/pdftext/scripts/extract_text.py
chunking_contrib/pdftext/settings.py
chunking_contrib/pdftext/tables.py
chunking_pdftext-0.6.2.post2.dist-info/LICENSE
chunking_pdftext-0.6.2.post2.dist-info/METADATA
chunking_pdftext-0.6.2.post2.dist-info/WHEEL
chunking_pdftext-0.6.2.post2.dist-info/entry_points.txt
chunking_pdftext-0.6.2.post2.dist-info/RECORD
